airtrain/__init__.py
airtrain/client.py
airtrain/core.py
airtrain/retry.py
airtrain/integrations/pandas.py
airtrain/integrations/polars.py
airtrain/integrations/llamaindex/__init__.py
airtrain/integrations/llamaindex/core.py
airtrain/integrations/llamaindex/tests/test_llamaindex_core.py
airtrain/integrations/tests/test_pandas.py
airtrain/integrations/tests/test_polars.py
airtrain_py-0.1.2.dist-info/LICENSE
airtrain_py-0.1.2.dist-info/METADATA
airtrain_py-0.1.2.dist-info/WHEEL
airtrain_py-0.1.2.dist-info/top_level.txt
airtrain_py-0.1.2.dist-info/RECORD
