Metadata-Version: 2.1
Name: airtrain-py
Version: 0.1.2
Summary: SDK for interacting with https://airtrain.ai
Author-email: support@airtrain.ai
License: Apache License
Project-URL: Homepage, https://airtrain.ai
Project-URL: Documentation, https://docs.airtrain.ai/
Project-URL: Repository, https://github.com/sematic-ai/py-airtrain
Classifier: License :: OSI Approved :: Apache Software License
Classifier: Intended Audience :: Developers
Classifier: Intended Audience :: Science/Research
Classifier: Topic :: Scientific/Engineering :: Artificial Intelligence
Classifier: Typing :: Typed
Classifier: Programming Language :: Python :: 3.8
Classifier: Programming Language :: Python :: 3.9
Classifier: Programming Language :: Python :: 3.10
Classifier: Programming Language :: Python :: 3.11
Classifier: Programming Language :: Python :: 3.12
Requires-Python: <4.0,>=3.8.1
License-File: LICENSE
Requires-Dist: httpx >=0.25.0
Requires-Dist: pyarrow >=13.0.0
Requires-Dist: numpy <=1.24.4 ; python_version == "3.8"
Requires-Dist: numpy >=1.26.0 ; python_version >= "3.12"
Requires-Dist: numpy >=1.19.3 ; python_version >= "3.9"
Provides-Extra: all
Requires-Dist: airtrain-py[llama-index,pandas,polars] ; extra == 'all'
Provides-Extra: llama-index
Requires-Dist: llama-index-core >=0.10.44 ; extra == 'llama-index'
Provides-Extra: pandas
Requires-Dist: pandas >=1.0.0 ; (python_version < "3.12") and extra == 'pandas'
Requires-Dist: pandas >=2.0.0 ; (python_version >= "3.12") and extra == 'pandas'
Provides-Extra: polars
Requires-Dist: polars >=0.19.0 ; extra == 'polars'
